wib/__init__.py
wib/__main__.py
wib/main.py
wib/clients/__init__.py
wib/clients/dns.py
wib/clients/ip2whois.py
wib/clients/ipwhois.py
wib/clients/rdap.py
wib/clients/whois.py
wib/config/__init__.py
wib/config/config.py
wib/handlers/__init__.py
wib/handlers/domain.py
wib/handlers/ipaddr.py
wib/http/request.py
wib/models/__init__.py
wib/models/common.py
wib/ui/__init__.py
wib/ui/render.py
wib/utils/__init__.py
wib/utils/defang.py
wib/utils/errors.py
wib/utils/validators.py
wib_osint-0.1.4.dist-info/METADATA
wib_osint-0.1.4.dist-info/WHEEL
wib_osint-0.1.4.dist-info/entry_points.txt
wib_osint-0.1.4.dist-info/top_level.txt
wib_osint-0.1.4.dist-info/RECORD
