Metadata-Version: 2.4
Name: wib-osint
Version: 0.1.4
Summary: Passive OSINT lookups for IPs and domains with a clean terminal UI
Author: tspry
License: MIT
Project-URL: Homepage, https://github.com/tspry/wib
Project-URL: Repository, https://github.com/tspry/wib
Keywords: osint,cli,security,whois,rdap,ip,domain
Requires-Python: >=3.10
Requires-Dist: httpx>=0.27.0
Requires-Dist: pydantic>=2.7.0
Requires-Dist: rich>=13.7.0
Requires-Dist: pyyaml>=6.0.1
Provides-Extra: dev
Requires-Dist: pytest>=7.4; extra == "dev"
Requires-Dist: pytest-asyncio>=0.23; extra == "dev"
Requires-Dist: respx>=0.21.1; extra == "dev"
Requires-Dist: coverage>=7.5; extra == "dev"
Requires-Dist: mypy>=1.10; extra == "dev"
Requires-Dist: ruff>=0.5.5; extra == "dev"
Requires-Dist: black>=24.8.0; extra == "dev"
Requires-Dist: isort>=5.13.2; extra == "dev"
Requires-Dist: bandit>=1.7.9; extra == "dev"
Requires-Dist: pre-commit>=3.7.0; extra == "dev"
Requires-Dist: types-PyYAML>=6.0.12; extra == "dev"
Requires-Dist: build>=1.2.1; extra == "dev"
Requires-Dist: twine>=5.1.1; extra == "dev"
Provides-Extra: all
